{
    "criterias": [
        {
            "contains": "ou"
        },
        {
            "ends_with": "z"
        },
        {
            "ends_with": "l"
        },
        {
            "starts_with": "n"
        },
        {
            "starts_with": "i"
        },
        {
            "starts_with": "v"
        }
    ],
    "solutions_points": [
        {
            "nansouk": 16,
            "nourrissait": 11,
            "niquedouille": 20,
            "nouassent": 9,
            "noueront": 8,
            "nouees": 6,
            "nouette": 7,
            "nourrie": 7,
            "noueux": 15,
            "nouasses": 8,
            "nouee": 5,
            "nourririez": 19,
            "nourriture": 10,
            "noubas": 8,
            "nioueennes": 10,
            "nourrisses": 10,
            "nouai": 5,
            "nouveaux": 20,
            "noueuses": 8,
            "nouassiez": 18,
            "nouerai": 7,
            "nouakchottois": 27,
            "nourriciere": 13,
            "nouveautes": 13,
            "nandous": 8,
            "nouassions": 10,
            "nourrissante": 12,
            "nouerais": 8,
            "nouveau": 10,
            "nourrirons": 10,
            "nourrisse": 9,
            "nouvelles": 12,
            "nouvelle": 11,
            "nourrissons": 11,
            "nourrirai": 9,
            "noumenal": 9,
            "nourrisson": 10,
            "nouvel": 9,
            "nouons": 6,
            "nourriront": 10,
            "noucs": 7,
            "nourrissages": 13,
            "noumeens": 9,
            "natoufien": 12,
            "nanzouk": 25,
            "noueurs": 7,
            "nourriraient": 12,
            "nourriras": 9,
            "noukta": 15,
            "nouais": 6,
            "nourriceries": 14,
            "nourrissants": 12,
            "natoufienne": 14,
            "nouvellistes": 15,
            "nourrices": 11,
            "nourriciers": 13,
            "nouchi": 11,
            "nouions": 7,
            "nitouches": 14,
            "nouakchottoises": 29,
            "noumenaux": 19,
            "nitouche": 13,
            "nioueens": 8,
            "nanzouks": 26,
            "noumenales": 11,
            "nouas": 5,
            "nouets": 6,
            "nouc": 6,
            "nouasse": 7,
            "noue": 4,
            "nourri": 6,
            "nouaisons": 9,
            "noua": 4,
            "noueraient": 10,
            "nouvelliste": 14,
            "nouerez": 16,
            "nourrirent": 10,
            "nourrirais": 10,
            "nourrice": 10,
            "niaoulis": 8,
            "noumenale": 10,
            "nourrissement": 14,
            "nourrissaient": 13,
            "nouba": 7,
            "nourririons": 11,
            "noucle": 8,
            "nourrisseurs": 12,
            "nourrit": 7,
            "nouiez": 15,
            "nourricier": 12,
            "nouures": 7,
            "nourrissant": 11,
            "nioueen": 7,
            "nouera": 6,
            "nouveaute": 12,
            "nouaient": 8,
            "nouements": 10,
            "nouames": 8,
            "nourrissez": 19,
            "nouat": 5,
            "nourrain": 8,
            "nourricieres": 14,
            "nouage": 7,
            "nougatines": 11,
            "nourrissements": 15,
            "noumeen": 8,
            "nourrirez": 18,
            "nourrissions": 12,
            "noumene": 8,
            "nandou": 7,
            "nouure": 6,
            "nounous": 7,
            "nougats": 8,
            "noueriez": 17,
            "natoufiennes": 15,
            "nouktas": 16,
            "nourrites": 9,
            "noueur": 6,
            "nouer": 5,
            "nourrissiez": 20,
            "noulets": 7,
            "nouilles": 8,
            "nourris": 7,
            "noumeenne": 10,
            "nougatine": 10,
            "niaouli": 7,
            "nouille": 7,
            "noulet": 6,
            "nourrimes": 10,
            "nouchis": 12,
            "nouerent": 8,
            "nouerait": 8,
            "nouates": 7,
            "nous": 4,
            "nansouks": 17,
            "nouet": 5,
            "nouent": 6,
            "nouerions": 9,
            "noucles": 9,
            "nouerons": 8,
            "nouait": 6,
            "niquedouilles": 21,
            "nouages": 8,
            "nourrisseur": 11,
            "noumenes": 9,
            "nouez": 14,
            "nourries": 8,
            "nourrir": 7,
            "nouvellement": 16,
            "nounours": 8,
            "noueras": 7,
            "natoufiens": 13,
            "nouement": 9,
            "noumeennes": 11,
            "nouaison": 8,
            "nourrains": 9,
            "nourrissantes": 13,
            "noueuse": 7,
            "nounou": 6,
            "nourricerie": 13,
            "nioueenne": 9,
            "nouakchottoise": 28,
            "noues": 5,
            "nourrissais": 11,
            "nourrissent": 11,
            "nourrissage": 12,
            "nourrirait": 10,
            "nourrira": 8,
            "nouant": 6,
            "nougat": 7,
            "nouettes": 8,
            "nourritures": 11
        },
        {
            "nobeliserez": 22,
            "naviguassiez": 25,
            "nattez": 15,
            "nordiriez": 19,
            "nuirez": 15,
            "numerotez": 19,
            "nimberez": 20,
            "narguassiez": 21,
            "noteriez": 17,
            "niassiez": 17,
            "noyauteriez": 29,
            "nickellerez": 31,
            "nanifierez": 22,
            "nagez": 15,
            "negociassiez": 24,
            "nidifiez": 21,
            "nantissez": 18,
            "negociiez": 21,
            "napperez": 21,
            "nichez": 20,
            "nationaliseriez": 24,
            "nippez": 19,
            "naufrageriez": 25,
            "niellerez": 18,
            "nombrez": 19,
            "neutralisez": 20,
            "necessiterez": 23,
            "nomadisez": 20,
            "neutraliseriez": 23,
            "noyautiez": 27,
            "niaquiez": 24,
            "neologiseriez": 23,
            "normalisassiez": 24,
            "novez": 17,
            "nacreriez": 20,
            "necrosassiez": 23,
            "naturaliseriez": 23,
            "niaquerez": 25,
            "notifierez": 22,
            "nouerez": 16,
            "novelliseriez": 25,
            "noviez": 18,
            "nappassiez": 23,
            "nominalisassiez": 25,
            "nasalisassiez": 22,
            "noterez": 16,
            "nuanceriez": 21,
            "novelisassiez": 25,
            "nobelisez": 20,
            "navriez": 19,
            "niveliez": 20,
            "nitrurassiez": 21,
            "nuerez": 15,
            "navettez": 20,
            "nanifiassiez": 24,
            "novellisiez": 23,
            "nebulisiez": 21,
            "normassiez": 20,
            "nitrassiez": 19,
            "novellisez": 22,
            "nickelassiez": 32,
            "nourrissiez": 20,
            "normerez": 18,
            "nattassiez": 19,
            "nettoyassiez": 30,
            "nasillerez": 19,
            "narguerez": 19,
            "numeroteriez": 22,
            "numeriseriez": 22,
            "nanisiez": 17,
            "nielleriez": 19,
            "navrerez": 20,
            "nebulisez": 20,
            "necroserez": 21,
            "nuancassiez": 22,
            "neologiserez": 22,
            "nationaliserez": 23,
            "nitrureriez": 20,
            "noyez": 23,
            "nacrez": 17,
            "niquiez": 23,
            "niaisez": 16,
            "nazifiiez": 30,
            "nordissez": 19,
            "nasalisiez": 19,
            "necessitez": 21,
            "nicherez": 22,
            "nolisassiez": 20,
            "negligiez": 20,
            "nueriez": 16,
            "naissez": 16,
            "noyautassiez": 30,
            "necessiteriez": 24,
            "naviguez": 21,
            "noyautez": 26,
            "nasillez": 17,
            "nettoyez": 26,
            "naturaliserez": 22,
            "nasilliez": 18,
            "nitrifiiez": 22,
            "nuisez": 15,
            "nucleariserez": 24,
            "niaiseriez": 19,
            "nickelerez": 30,
            "niquassiez": 26,
            "nichiez": 21,
            "nasonnez": 17,
            "necessitiez": 22,
            "notiez": 15,
            "navrassiez": 22,
            "niquez": 22,
            "nucleariseriez": 25,
            "notifieriez": 23,
            "nasonniez": 18,
            "nationalisez": 21,
            "navigueriez": 24,
            "nickeliez": 29,
            "nouassiez": 18,
            "neantiseriez": 21,
            "nacrerez": 19,
            "numeroterez": 21,
            "nacrassiez": 21,
            "numerisez": 19,
            "narreriez": 18,
            "noircissiez": 22,
            "nordissiez": 20,
            "nasaliseriez": 21,
            "nanisassiez": 20,
            "negociez": 20,
            "nuancerez": 20,
            "nipperez": 21,
            "nombreriez": 22,
            "niaquez": 23,
            "nuancez": 18,
            "naufrageassiez": 27,
            "novelliserez": 24,
            "noveriez": 20,
            "nidifieriez": 24,
            "nobeliseriez": 23,
            "nuisiez": 16,
            "nuclearisez": 22,
            "navetterez": 22,
            "naturalisiez": 21,
            "nickelez": 28,
            "nettoieriez": 20,
            "nageotez": 18,
            "naitriez": 17,
            "nivelez": 19,
            "nippiez": 20,
            "novellisassiez": 26,
            "nageotassiez": 22,
            "naturalisez": 20,
            "niaqueriez": 26,
            "negligez": 19,
            "neologisez": 20,
            "nitratiez": 18,
            "nourrissez": 19,
            "niiez": 14,
            "natteriez": 18,
            "nitrosiez": 18,
            "nantiriez": 18,
            "nordirez": 18,
            "nageoterez": 20,
            "necessitassiez": 25,
            "negocierez": 22,
            "nitrifierez": 23,
            "nombrassiez": 23,
            "nominerez": 19,
            "noceriez": 19,
            "narguez": 17,
            "navreriez": 21,
            "noierez": 16,
            "nasonneriez": 20,
            "nickeleriez": 31,
            "numerisassiez": 23,
            "numeriserez": 21,
            "notez": 14,
            "neantiserez": 20,
            "nouez": 14,
            "neantisassiez": 22,
            "necrosez": 19,
            "noveliserez": 23,
            "normiez": 17,
            "narrassiez": 19,
            "niellassiez": 20,
            "naitrez": 16,
            "nappiez": 20,
            "nociez": 17,
            "nocassiez": 20,
            "nidifiiez": 22,
            "narriez": 16,
            "nervuriez": 21,
            "navettiez": 21,
            "nuisissiez": 19,
            "nationalisiez": 22,
            "nitrosassiez": 21,
            "novassiez": 21,
            "negocieriez": 23,
            "nazifiez": 29,
            "nidifierez": 23,
            "notifiassiez": 24,
            "navetteriez": 23,
            "nebulisassiez": 24,
            "notifiiez": 21,
            "noliserez": 18,
            "nourririez": 19,
            "nonupliez": 20,
            "neantisez": 18,
            "nuclearisassiez": 26,
            "neutralisassiez": 24,
            "normalisiez": 21,
            "nippassiez": 23,
            "nappez": 19,
            "nitraterez": 19,
            "normaliseriez": 23,
            "nazifiassiez": 33,
            "nomadiserez": 22,
            "nivelerez": 21,
            "nantirez": 17,
            "niez": 13,
            "nitroseriez": 20,
            "nivellerez": 22,
            "nuez": 13,
            "neutralisiez": 21,
            "notassiez": 18,
            "nasilleriez": 20,
            "negligeriez": 22,
            "nominassiez": 21,
            "nervurassiez": 24,
            "nervurerez": 22,
            "nagiez": 16,
            "nimbassiez": 22,
            "nationalisassiez": 25,
            "nonuplerez": 21,
            "naufragiez": 23,
            "nitrifiassiez": 25,
            "nonuplez": 19,
            "nuassiez": 17,
            "noveliseriez": 24,
            "nitreriez": 18,
            "nitrateriez": 20,
            "noyiez": 24,
            "naufragez": 22,
            "niellez": 16,
            "niveleriez": 22,
            "nonuplassiez": 23,
            "nettoyiez": 27,
            "nommassiez": 21,
            "nominalisiez": 22,
            "normaliserez": 22,
            "nomadiseriez": 23,
            "nicheriez": 23,
            "nuiriez": 16,
            "naquissiez": 26,
            "nazifieriez": 32,
            "nourrirez": 18,
            "noyassiez": 27,
            "nominalisez": 21,
            "nargueriez": 20,
            "negligeassiez": 24,
            "numerotassiez": 23,
            "noueriez": 17,
            "neologisassiez": 24,
            "neantisiez": 19,
            "nuclearisiez": 23,
            "nominiez": 18,
            "nidifiassiez": 25,
            "nipperiez": 22,
            "nocerez": 18,
            "nasaliserez": 20,
            "nierez": 15,
            "nitriez": 16,
            "noircissez": 21,
            "nommez": 17,
            "narguiez": 18,
            "nitrurez": 17,
            "nominaliseriez": 24,
            "nitrosez": 17,
            "nantissiez": 19,
            "nitrifiez": 21,
            "nitruriez": 18,
            "notifiez": 20,
            "nieriez": 16,
            "nanifiez": 20,
            "nolisez": 16,
            "noircirez": 20,
            "naniserez": 18,
            "nomadisiez": 21,
            "nasonnassiez": 21,
            "niaquassiez": 27,
            "nasalisez": 18,
            "nimbez": 18,
            "nattiez": 16,
            "navrez": 18,
            "nommerez": 19,
            "nitrifieriez": 24,
            "nitrerez": 17,
            "nagerez": 17,
            "nominaliserez": 23,
            "nervurez": 20,
            "noyauterez": 28,
            "nichassiez": 24,
            "nobelisassiez": 24,
            "nageriez": 18,
            "nickelleriez": 32,
            "neologisiez": 21,
            "nanifiiez": 21,
            "nitratez": 17,
            "nebuliseriez": 23,
            "nageotiez": 19,
            "novelisiez": 22,
            "nervureriez": 23,
            "nomadisassiez": 24,
            "nocez": 16,
            "noieriez": 17,
            "navettassiez": 24,
            "nombrerez": 21,
            "noverez": 19,
            "naissiez": 17,
            "nommiez": 18,
            "numerotiez": 20,
            "nielliez": 17,
            "nivelleriez": 23,
            "nitrurerez": 19,
            "normeriez": 19,
            "nomineriez": 20,
            "nombriez": 20,
            "nuanciez": 19,
            "noirciriez": 21,
            "napperiez": 22,
            "nebuliserez": 22,
            "narrez": 15,
            "niaisiez": 17,
            "niqueriez": 25,
            "natterez": 17,
            "nonupleriez": 22,
            "nouiez": 15,
            "nasillassiez": 21,
            "niquerez": 24,
            "nitratassiez": 21,
            "naufragerez": 24,
            "nageassiez": 20,
            "naturalisassiez": 24,
            "necrosiez": 20,
            "naniseriez": 19,
            "nitrez": 15,
            "naviguerez": 23,
            "nettoierez": 19,
            "nivelassiez": 23,
            "noliseriez": 19,
            "nommeriez": 20,
            "nitroserez": 19,
            "novelisez": 21,
            "nacriez": 18,
            "niaisassiez": 20,
            "normez": 16,
            "neutraliserez": 22,
            "nageoteriez": 21,
            "narrerez": 17,
            "nasonnerez": 19,
            "naviguiez": 22,
            "nuiez": 14,
            "nazifierez": 31,
            "niaiserez": 18,
            "nobelisiez": 21,
            "nanisez": 16,
            "nimbiez": 19,
            "negligerez": 21,
            "nez": 12,
            "necroseriez": 22,
            "numerisiez": 20,
            "nominez": 17,
            "nanifieriez": 23,
            "nimberiez": 21,
            "nolisiez": 17,
            "normalisez": 20
        },
        {
            "nocturnal": 11,
            "natal": 5,
            "noel": 4,
            "nemoral": 8,
            "nombril": 10,
            "nadiral": 8,
            "nahuatl": 10,
            "nucal": 7,
            "nominal": 8,
            "nonpareil": 11,
            "nuptial": 9,
            "nosocomial": 13,
            "notarial": 8,
            "nasal": 5,
            "nuchal": 11,
            "narval": 9,
            "nycthemeral": 26,
            "neorural": 8,
            "nul": 3,
            "neuronal": 8,
            "naphtol": 12,
            "national": 8,
            "neonatal": 8,
            "nell": 4,
            "nivopluvial": 19,
            "nutritionnel": 12,
            "neoliberal": 12,
            "natel": 5,
            "neufchatel": 18,
            "nickel": 17,
            "niveal": 9,
            "nodal": 6,
            "nymphal": 22,
            "neural": 6,
            "neuchatel": 14,
            "neolocal": 10,
            "naval": 8,
            "naturel": 7,
            "neocortical": 15,
            "nobel": 7,
            "noumenal": 9,
            "nouvel": 9,
            "nicol": 7,
            "nopal": 7,
            "netball": 9,
            "normal": 7,
            "nival": 8,
            "numeral": 8,
            "navel": 8,
            "notionnel": 9,
            "napel": 7,
            "negrospiritual": 17
        },
        {
            "ioulat": 6,
            "intercourses": 14,
            "injouables": 19,
            "ioulerais": 9,
            "ioulent": 7,
            "improuverions": 19,
            "infrarouge": 14,
            "ingouvernable": 19,
            "improuverez": 26,
            "improuveras": 17,
            "ioula": 5,
            "indouistes": 11,
            "inabouti": 10,
            "inavouee": 11,
            "insoutenable": 14,
            "inoubliable": 15,
            "insouciante": 13,
            "irrecouvrable": 20,
            "ioule": 5,
            "indouismes": 12,
            "indouiste": 10,
            "improuvez": 24,
            "inecoutable": 15,
            "ioulerions": 10,
            "insouciants": 13,
            "improuvera": 16,
            "ineprouvee": 15,
            "insouciance": 15,
            "inforoute": 12,
            "indeboulonnable": 20,
            "insoucieux": 21,
            "inoui": 5,
            "inouie": 6,
            "inoubliables": 16,
            "injouable": 18,
            "improuvasses": 18,
            "intouche": 13,
            "ioulais": 7,
            "ioulasse": 8,
            "ioulerons": 9,
            "ioulames": 9,
            "itou": 4,
            "iglou": 6,
            "indebrouillable": 20,
            "inaccoutumes": 17,
            "intouches": 14,
            "insoumise": 10,
            "inabouties": 12,
            "improuvassent": 19,
            "intouchable": 18,
            "indeboulonnables": 21,
            "indouisme": 11,
            "inaboutis": 11,
            "ineprouves": 15,
            "ioulassions": 11,
            "ioules": 6,
            "improuverais": 18,
            "improuvas": 15,
            "ingouche": 14,
            "intercours": 12,
            "inavouables": 16,
            "inaccoutumee": 17,
            "insoumission": 13,
            "incontournables": 19,
            "inaccoutume": 16,
            "inaboutie": 11,
            "indous": 7,
            "insoucieuse": 13,
            "indebrouillables": 21,
            "insoupconnable": 20,
            "improuver": 15,
            "improuverait": 18,
            "improuves": 15,
            "insoulevable": 17,
            "insoupconnes": 16,
            "ioulas": 6,
            "iouleraient": 11,
            "improuvable": 19,
            "intouchables": 19,
            "irrecouvrables": 21,
            "inavouable": 15,
            "improuvons": 16,
            "infoutu": 10,
            "introuvable": 16,
            "ingouvernables": 20,
            "introuvables": 17,
            "insoupconnees": 17,
            "inaccoutumances": 22,
            "intouchees": 15,
            "improuverons": 18,
            "ioulerai": 8,
            "inassouvissables": 21,
            "ioulasses": 9,
            "insoumises": 11,
            "intergroupe": 14,
            "inassouvi": 12,
            "inlouables": 12,
            "improuveront": 18,
            "indenouable": 14,
            "inassouvissable": 20,
            "irouleguys": 20,
            "improuveraient": 20,
            "improuvai": 15,
            "improuverai": 17,
            "insoucieuses": 14,
            "ioulez": 15,
            "improuvant": 16,
            "improuviez": 25,
            "iouliez": 16,
            "improuvasse": 17,
            "insoumissions": 14,
            "iglous": 7,
            "incontournable": 18,
            "inaccoutumance": 21,
            "ioulai": 6,
            "infoutue": 11,
            "ioulassent": 10,
            "ioulerez": 17,
            "inecoutee": 11,
            "indenouables": 15,
            "insoulevables": 18,
            "inassouvis": 13,
            "iouler": 6,
            "intouchee": 14,
            "indoues": 8,
            "inouis": 6,
            "inassouvie": 13,
            "improuvables": 20,
            "ioulera": 7,
            "inavoue": 10,
            "inavouees": 12,
            "inforoutes": 13,
            "improuvaient": 18,
            "ineprouvees": 16,
            "ioulant": 7,
            "ingouches": 15,
            "ioulates": 8,
            "improuvassiez": 28,
            "iourtes": 7,
            "inaccoutumees": 18,
            "inecoutables": 16,
            "insouciant": 12,
            "ioulassiez": 19,
            "improuvais": 16,
            "inecoute": 10,
            "inecoutes": 11,
            "iakoutes": 17,
            "insoutenables": 15,
            "ioulait": 7,
            "iouleront": 9,
            "ioulons": 7,
            "infoutues": 12,
            "insouciantes": 14,
            "improuva": 14,
            "improuverent": 18,
            "indou": 6,
            "irouleguy": 19,
            "improuvassions": 20,
            "ineprouve": 14,
            "improuvions": 17,
            "improuvames": 18,
            "improuvates": 17,
            "intercourse": 13,
            "improuveriez": 27,
            "improuve": 14,
            "insoupconnee": 16,
            "improuvee": 15,
            "insoupconne": 15,
            "insoumis": 9,
            "inecoutees": 12,
            "improuvat": 15,
            "intergroupes": 15,
            "inassouvies": 14,
            "insoupconnables": 21,
            "iouleras": 8,
            "iouleriez": 18,
            "iourte": 6,
            "insouciances": 16,
            "improuvait": 16,
            "inavoues": 11,
            "infoutus": 11,
            "ioulions": 8,
            "improuvent": 16,
            "iakoute": 16,
            "inouies": 7,
            "ioulerent": 9,
            "improuvees": 16,
            "infrarouges": 15,
            "inlouable": 11,
            "ioulerait": 9,
            "ioulaient": 9,
            "indoue": 7
        },
        {
            "infirmez": 21,
            "idolatrassiez": 23,
            "induisez": 18,
            "influiez": 20,
            "inculquez": 27,
            "integreriez": 21,
            "inclinerez": 21,
            "impliqueriez": 31,
            "interessiez": 20,
            "impartirez": 22,
            "ignorerez": 19,
            "interrogeriez": 23,
            "inviteriez": 22,
            "ironisassiez": 21,
            "insupportassiez": 28,
            "imiteriez": 19,
            "interclassiez": 24,
            "introjectez": 29,
            "illustriez": 19,
            "immatriculerez": 27,
            "immiscassiez": 25,
            "incubez": 20,
            "initialiseriez": 23,
            "inciteriez": 21,
            "intervinssiez": 25,
            "impliquerez": 30,
            "incisiez": 19,
            "insensibilisassiez": 29,
            "infiltriez": 22,
            "imprimeriez": 24,
            "infantilisassiez": 28,
            "insolubilisez": 24,
            "incrementez": 23,
            "infantiliserez": 26,
            "improuvez": 24,
            "indiffereriez": 29,
            "inserez": 16,
            "inculquiez": 28,
            "interjetteriez": 30,
            "inauguriez": 20,
            "italianiserez": 22,
            "immigrez": 20,
            "indexerez": 28,
            "impregnerez": 24,
            "indemniserez": 23,
            "inhumassiez": 24,
            "insistiez": 18,
            "instiguez": 19,
            "immatriculez": 25,
            "intoxiquassiez": 39,
            "invisibiliseriez": 30,
            "impermeabilisiez": 31,
            "inhumez": 20,
            "interneriez": 20,
            "ionisassiez": 20,
            "influencassiez": 28,
            "imputiez": 20,
            "inalpez": 18,
            "instruirez": 19,
            "instruisez": 19,
            "inaugureriez": 22,
            "inspectassiez": 26,
            "insonorisiez": 21,
            "insufflerez": 26,
            "interceptiez": 25,
            "invectivassiez": 31,
            "innervassiez": 24,
            "interesserez": 21,
            "iodleriez": 19,
            "intriguiez": 20,
            "inversiez": 21,
            "instillerez": 20,
            "interceptez": 24,
            "iodiez": 16,
            "infiltrerez": 23,
            "inspirassiez": 23,
            "injectez": 26,
            "illuterez": 18,
            "indiquiez": 26,
            "inquietez": 25,
            "intimeriez": 20,
            "innocentez": 21,
            "insulteriez": 20,
            "infatuerez": 22,
            "iteriez": 16,
            "implorassiez": 24,
            "incendiassiez": 25,
            "infiltrez": 21,
            "invalidez": 22,
            "inaugurez": 19,
            "internassiez": 21,
            "illuminassiez": 23,
            "imposassiez": 23,
            "inoculiez": 20,
            "intailliez": 19,
            "intriguerez": 21,
            "infestiez": 21,
            "intercepterez": 26,
            "immisceriez": 24,
            "incluiez": 19,
            "injuriez": 24,
            "immoliez": 19,
            "idiotifieriez": 26,
            "improviserez": 27,
            "ignifugeriez": 26,
            "instaurerez": 20,
            "intaillerez": 20,
            "introjectassiez": 33,
            "instruisiez": 20,
            "incrementerez": 25,
            "impatronisassiez": 28,
            "interconnecteriez": 30,
            "industrialisassiez": 28,
            "intimassiez": 21,
            "initialiez": 19,
            "intervertirez": 25,
            "incarniez": 20,
            "innovez": 19,
            "interpoleriez": 24,
            "introduisiez": 22,
            "interdirez": 20,
            "indianiseriez": 23,
            "imbiberez": 23,
            "incrementeriez": 26,
            "incarnerez": 21,
            "institueriez": 21,
            "islamisez": 19,
            "indexiez": 27,
            "inhalassiez": 23,
            "indisposerez": 24,
            "illuminerez": 21,
            "instaurassiez": 22,
            "illutez": 16,
            "instrumenterez": 24,
            "imbriquerez": 30,
            "immobiliseriez": 27,
            "infectiez": 23,
            "initialez": 18,
            "innerverez": 22,
            "interviewez": 32,
            "inventerez": 22,
            "idealiseriez": 22,
            "invaliderez": 24,
            "irritassiez": 20,
            "immigrassiez": 24,
            "immergerez": 22,
            "impetreriez": 23,
            "inactiviez": 24,
            "incorporassiez": 27,
            "informatisiez": 26,
            "implorerez": 22,
            "intercaleriez": 24,
            "inactiverez": 25,
            "intercalassiez": 25,
            "impatientez": 23,
            "inaugurerez": 21,
            "ioulez": 15,
            "imaginassiez": 23,
            "injuriassiez": 28,
            "implantassiez": 25,
            "indentez": 18,
            "interposerez": 23,
            "inerterez": 18,
            "imbriquiez": 29,
            "illustreriez": 21,
            "invetererez": 23,
            "idealisassiez": 23,
            "italianisassiez": 24,
            "idiotifiiez": 24,
            "individualisez": 28,
            "immatriculassiez": 29,
            "innocentassiez": 25,
            "incendiiez": 22,
            "insensibiliserez": 27,
            "illuminiez": 20,
            "imputassiez": 23,
            "imageriez": 20,
            "intituleriez": 21,
            "invalidassiez": 26,
            "incuberez": 22,
            "infecterez": 24,
            "isolassiez": 19,
            "inciserez": 20,
            "intuiteriez": 20,
            "incommodiez": 25,
            "incisassiez": 22,
            "instituerez": 20,
            "introspecteriez": 28,
            "introspectez": 25,
            "indigneriez": 22,
            "infererez": 21,
            "invertissez": 23,
            "imploriez": 21,
            "impactassiez": 26,
            "impulserez": 22,
            "implementez": 24,
            "illusionniez": 21,
            "intercalez": 21,
            "interpeliez": 22,
            "introspectassiez": 29,
            "inculpassiez": 25,
            "intriquerez": 27,
            "irisiez": 16,
            "inhiberez": 23,
            "indexassiez": 30,
            "imagineriez": 22,
            "immigriez": 21,
            "immolez": 18,
            "impregneriez": 25,
            "ingenieriez": 21,
            "initialisassiez": 24,
            "interfacassiez": 28,
            "interrompez": 23,
            "intuitiez": 18,
            "ioulassiez": 19,
            "interclasseriez": 26,
            "inciseriez": 21,
            "inscrirez": 20,
            "instigueriez": 22,
            "incrustez": 20,
            "interfolierez": 25,
            "interviewerez": 34,
            "intailleriez": 21,
            "inculquassiez": 31,
            "instillassiez": 22,
            "inclineriez": 22,
            "industrialisiez": 25,
            "intriguassiez": 23,
            "imposeriez": 22,
            "islamisiez": 20,
            "indurassiez": 21,
            "impacteriez": 25,
            "itererez": 17,
            "improvisez": 25,
            "individualiseriez": 31,
            "infeodassiez": 25,
            "ingurgitez": 21,
            "intervieweriez": 35,
            "incardineriez": 25,
            "internalisassiez": 25,
            "incriminassiez": 26,
            "initierez": 18,
            "interpreterez": 24,
            "intimidez": 20,
            "indentiez": 19,
            "irrigueriez": 21,
            "introjectiez": 30,
            "infarcirez": 24,
            "idealisiez": 20,
            "imitiez": 17,
            "immortalisassiez": 27,
            "inoculeriez": 22,
            "interviendriez": 27,
            "irriteriez": 19,
            "insurgerez": 20,
            "incarneriez": 22,
            "intercedez": 22,
            "interfereriez": 25,
            "invisibilisez": 27,
            "iodlassiez": 20,
            "intensifierez": 25,
            "impetrez": 20,
            "implementeriez": 27,
            "induisiez": 19,
            "infiltrassiez": 25,
            "interiorisez": 21,
            "interjetterez": 29,
            "irriterez": 18,
            "interclasserez": 25,
            "incriminez": 22,
            "iriserez": 17,
            "insinueriez": 20,
            "incinerassiez": 24,
            "internerez": 19,
            "infligerez": 23,
            "incinereriez": 23,
            "introduirez": 21,
            "illustrez": 18,
            "ionisez": 16,
            "irez": 13,
            "illustrerez": 20,
            "insolubilisassiez": 28,
            "iodez": 15,
            "importuniez": 23,
            "invalideriez": 25,
            "insonorisassiez": 24,
            "indaguerez": 21,
            "improvisiez": 26,
            "implanteriez": 24,
            "imagiez": 18,
            "impactez": 22,
            "invoquez": 27,
            "impressionneriez": 28,
            "ingurgiteriez": 24,
            "insolubiliseriez": 27,
            "indaguiez": 20,
            "insistassiez": 21,
            "interpreteriez": 25,
            "insupportez": 24,
            "invitiez": 20,
            "infantiliseriez": 27,
            "iterassiez": 19,
            "ixez": 22,
            "imposerez": 21,
            "incarcerassiez": 27,
            "inhibiez": 22,
            "immobilisassiez": 28,
            "invoqueriez": 30,
            "invectiveriez": 30,
            "intriguez": 19,
            "infeodez": 21,
            "importunassiez": 26,
            "incardinerez": 24,
            "induirez": 18,
            "immergiez": 21,
            "imiterez": 18,
            "immortaliserez": 25,
            "inactivassiez": 27,
            "initialeriez": 21,
            "implementerez": 26,
            "instrumentassiez": 26,
            "insuffliez": 25,
            "interpenetrassiez": 28,
            "interessez": 19,
            "intronisez": 19,
            "intronisassiez": 23,
            "ixiez": 23,
            "indignerez": 21,
            "inalperez": 20,
            "impliquez": 28,
            "indicerez": 21,
            "inertassiez": 20,
            "immunisiez": 21,
            "infeoderez": 23,
            "insecurisassiez": 26,
            "infarcissez": 25,
            "identifierez": 25,
            "idealisez": 19,
            "interagiriez": 22,
            "incardiniez": 23,
            "interrompiez": 24,
            "infatueriez": 23,
            "inondez": 17,
            "indicez": 19,
            "incineriez": 21,
            "instiguiez": 20,
            "inactivez": 23,
            "interpolez": 21,
            "infligiez": 22,
            "indemnisez": 21,
            "intronisiez": 20,
            "impermeabilisassiez": 34,
            "innervez": 20,
            "implorez": 20,
            "incommodassiez": 28,
            "imagerez": 19,
            "indemnisassiez": 25,
            "intuiterez": 19,
            "introduisissiez": 25,
            "introniseriez": 22,
            "interclassassiez": 27,
            "interesseriez": 22,
            "interposassiez": 25,
            "inhumerez": 22,
            "installassiez": 22,
            "inculquerez": 29,
            "infibuliez": 24,
            "ingereriez": 20,
            "iodlez": 16,
            "invertirez": 22,
            "inculperiez": 24,
            "incrustiez": 21,
            "infectez": 22,
            "inspectez": 22,
            "inonderiez": 20,
            "investigueriez": 27,
            "incriminerez": 24,
            "incorporiez": 24,
            "indenteriez": 21,
            "imbibiez": 22,
            "intentassiez": 21,
            "interrogez": 20,
            "insurgez": 18,
            "influeriez": 22,
            "interpenetrez": 24,
            "inalpassiez": 22,
            "inferiorisez": 24,
            "ingerez": 17,
            "inferioriseriez": 27,
            "insonorisez": 20,
            "infusassiez": 23,
            "impregnez": 22,
            "interjetassiez": 30,
            "introniserez": 21,
            "illutiez": 17,
            "inquietiez": 26,
            "iriseriez": 18,
            "importuneriez": 25,
            "indiciez": 20,
            "intervertissez": 26,
            "intriquez": 25,
            "influassiez": 23,
            "interposiez": 22,
            "investirez": 22,
            "impartissez": 23,
            "insonoriseriez": 23,
            "inspecterez": 24,
            "interrogeassiez": 25,
            "impacterez": 24,
            "invisibilisassiez": 31,
            "inculperez": 23,
            "illusionnez": 20,
            "influenceriez": 27,
            "iterez": 15,
            "inventiez": 21,
            "interlignerez": 23,
            "indulgenciez": 25,
            "inspirerez": 21,
            "interioriserez": 23,
            "insultiez": 18,
            "interfererez": 24,
            "identifiez": 23,
            "improvisassiez": 29,
            "insemineriez": 22,
            "informerez": 23,
            "insinuerez": 19,
            "invagineriez": 25,
            "immolerez": 20,
            "ioniseriez": 19,
            "installez": 18,
            "intimez": 17,
            "interessassiez": 23,
            "infibulassiez": 27,
            "indisposeriez": 25,
            "interromprez": 24,
            "imageassiez": 22,
            "interceptassiez": 28,
            "iouliez": 16,
            "ironisiez": 18,
            "infiltreriez": 24,
            "innocenteriez": 24,
            "instilliez": 19,
            "isolerez": 17,
            "iodlerez": 18,
            "intellectualisez": 27,
            "indiquez": 25,
            "intercedassiez": 26,
            "infirmeriez": 24,
            "interdisiez": 21,
            "infroissabilisez": 30,
            "indigniez": 20,
            "invaginerez": 24,
            "incorporerez": 25,
            "infarcissiez": 26,
            "immobilisiez": 25,
            "inclussiez": 21,
            "informatiseriez": 28,
            "impatroniserez": 26,
            "ingeriez": 18,
            "ingurgitassiez": 25,
            "instiguassiez": 23,
            "ioderez": 17,
            "interligneriez": 24,
            "infroissabiliserez": 32,
            "intercederez": 24,
            "invoquassiez": 31,
            "impatienterez": 25,
            "inhumiez": 21,
            "insupportiez": 25,
            "imputez": 19,
            "intervertissiez": 27,
            "impliquiez": 29,
            "innoviez": 20,
            "imitez": 16,
            "incubiez": 21,
            "internez": 17,
            "improuvassiez": 28,
            "insurgiez": 19,
            "initieriez": 19,
            "inertez": 16,
            "indenterez": 20,
            "intitulassiez": 22,
            "interfaceriez": 27,
            "invectiviez": 28,
            "inventoriez": 23,
            "infatuassiez": 24,
            "intenteriez": 20,
            "invitassiez": 23,
            "insurgeriez": 21,
            "indexeriez": 29,
            "injectiez": 27,
            "irriguassiez": 22,
            "itereriez": 18,
            "inhiberiez": 24,
            "intensifieriez": 26,
            "inhibassiez": 25,
            "indianisez": 20,
            "immoleriez": 21,
            "inflechiriez": 29,
            "inferez": 19,
            "indisposassiez": 26,
            "insecuriserez": 24,
            "impermeabilisez": 30,
            "importunerez": 24,
            "influencez": 24,
            "interfoliassiez": 27,
            "iriez": 14,
            "imaginez": 19,
            "instilleriez": 21,
            "implantez": 21,
            "interpeleriez": 24,
            "ixerez": 24,
            "instruiriez": 20,
            "intimerez": 19,
            "immolassiez": 22,
            "instituez": 18,
            "inscriviez": 24,
            "impartissiez": 24,
            "implosassiez": 24,
            "incarcereriez": 26,
            "imbiberiez": 24,
            "initialassiez": 22,
            "innovassiez": 23,
            "interpellez": 22,
            "impetrassiez": 24,
            "inculpez": 21,
            "iouleriez": 18,
            "intriquassiez": 29,
            "indulgenciassiez": 29,
            "interloquerez": 29,
            "illusionneriez": 23,
            "impulsiez": 21,
            "italianisiez": 21,
            "infestez": 20,
            "immunisassiez": 24,
            "invaginassiez": 26,
            "infligeriez": 24,
            "investiguassiez": 28,
            "impatienteriez": 26,
            "infroissabilisiez": 31,
            "incarnez": 19,
            "ingeniez": 18,
            "idolatriez": 20,
            "ironiseriez": 20,
            "incitez": 18,
            "insculpiez": 23,
            "interviewiez": 33,
            "implosiez": 21,
            "interjetez": 26,
            "inferioriserez": 26,
            "interagirez": 21,
            "interdisez": 20,
            "impatientiez": 24,
            "irradiez": 18,
            "initiez": 16,
            "implementiez": 25,
            "insufflez": 24,
            "impatronisiez": 25,
            "incisez": 18,
            "invisibilisiez": 28,
            "internaliseriez": 24,
            "instrumenteriez": 25,
            "introjecterez": 31,
            "italianisez": 20,
            "inertiez": 17,
            "infesteriez": 23,
            "immiscez": 21,
            "improuverez": 26,
            "identifiassiez": 27,
            "imbibassiez": 25,
            "inhalerez": 21,
            "impatronisez": 24,
            "inspiriez": 20,
            "inventorieriez": 26,
            "immortaliseriez": 26,
            "insecurisez": 22,
            "investiguez": 24,
            "intensifiassiez": 27,
            "inactiveriez": 26,
            "interloquez": 27,
            "inalpiez": 19,
            "instrumentiez": 23,
            "interpellerez": 24,
            "isolez": 15,
            "infligeassiez": 26,
            "implementassiez": 28,
            "immobiliserez": 26,
            "invisibiliserez": 29,
            "injuriiez": 25,
            "inverseriez": 23,
            "innerveriez": 23,
            "intoxiquez": 35,
            "indisposez": 22,
            "inferassiez": 23,
            "insolubiliserez": 26,
            "inoculez": 19,
            "intuitez": 17,
            "incurvez": 22,
            "insensibilisiez": 26,
            "interpenetriez": 25,
            "incurveriez": 25,
            "islamiseriez": 22,
            "indicassiez": 23,
            "imbriquez": 28,
            "insistez": 17,
            "industrialisez": 24,
            "indureriez": 20,
            "inflechissiez": 30,
            "impliquassiez": 32,
            "individualisiez": 29,
            "intitulerez": 20,
            "iodassiez": 19,
            "inhalez": 19,
            "initialiserez": 22,
            "impetriez": 21,
            "impressionnerez": 27,
            "ignoreriez": 20,
            "ignifugiez": 24,
            "intellectualisiez": 28,
            "interfoliez": 23,
            "insultassiez": 21,
            "imagez": 17,
            "inculqueriez": 30,
            "impregnassiez": 26,
            "inseminez": 19,
            "incommoderiez": 27,
            "inscrivez": 23,
            "interdiriez": 21,
            "interferassiez": 26,
            "impulseriez": 23,
            "informeriez": 24,
            "irritiez": 17,
            "incarceriez": 24,
            "inveteriez": 22,
            "intituliez": 19,
            "induiriez": 19,
            "informiez": 22,
            "insisterez": 19,
            "interpelleriez": 25,
            "intuberiez": 21,
            "infatuiez": 21,
            "identifiiez": 24,
            "impressionnassiez": 29,
            "impulsez": 20,
            "interagissez": 22,
            "indignez": 19,
            "importeriez": 23,
            "idiotifierez": 25,
            "indulgenciiez": 26,
            "inclinassiez": 23,
            "interlignez": 21,
            "insolez": 16,
            "importez": 20,
            "immigreriez": 23,
            "identifieriez": 26,
            "informassiez": 25,
            "immortalisez": 23,
            "inclinez": 19,
            "incrusterez": 22,
            "individualiserez": 30,
            "indemnisiez": 22,
            "inflechirez": 28,
            "instrumentaliserez": 28,
            "intellectualiserez": 29,
            "idiotifiez": 23,
            "insolerez": 18,
            "installeriez": 21,
            "intitulez": 18,
            "inviterez": 21,
            "infuserez": 21,
            "individualisassiez": 32,
            "investiguiez": 25,
            "inaugurassiez": 23,
            "impulsassiez": 24,
            "imitassiez": 20,
            "intubassiez": 22,
            "ironiserez": 19,
            "interligniez": 22,
            "immergeassiez": 25,
            "indisposiez": 23,
            "immatriculeriez": 28,
            "irisassiez": 19,
            "isomerisiez": 21,
            "impressionniez": 26,
            "immortalisiez": 24,
            "initialisiez": 21,
            "irradiassiez": 22,
            "interpelassiez": 25,
            "intercaliez": 22,
            "introspectiez": 26,
            "insisteriez": 20,
            "inspectiez": 23,
            "intercediez": 23,
            "incinererez": 22,
            "intuberez": 20,
            "ignorassiez": 21,
            "interclassez": 23,
            "inhibez": 21,
            "intenterez": 19,
            "impatroniseriez": 27,
            "insoleriez": 19,
            "interfaciez": 25,
            "inciterez": 20,
            "indianisassiez": 24,
            "inferiorisassiez": 28,
            "inventassiez": 24,
            "islamiserez": 21,
            "ingeniassiez": 22,
            "infusez": 19,
            "insurgeassiez": 23,
            "interiorisiez": 22,
            "interrompriez": 25,
            "incliniez": 20,
            "insupporteriez": 27,
            "inspireriez": 22,
            "idolatrerez": 21,
            "interpolassiez": 25,
            "interpretiez": 23,
            "inhaleriez": 22,
            "isoliez": 16,
            "interloqueriez": 30,
            "irradiiez": 19,
            "incommodez": 24,
            "inspirez": 19,
            "ioniserez": 18,
            "inondiez": 18,
            "incrusteriez": 23,
            "indagueriez": 22,
            "industrialiserez": 26,
            "importiez": 21,
            "influencerez": 26,
            "indentassiez": 22,
            "italianiseriez": 23,
            "industrialiseriez": 27,
            "inserassiez": 20,
            "inseminerez": 21,
            "imposiez": 20,
            "installerez": 20,
            "impartiriez": 23,
            "intubiez": 19,
            "integriez": 19,
            "imploseriez": 23,
            "idolatreriez": 22,
            "invoquerez": 29,
            "injectassiez": 30,
            "inscrivissiez": 27,
            "inversez": 20,
            "infecteriez": 25,
            "idiotifiassiez": 27,
            "implosez": 20,
            "infectassiez": 26,
            "insculperiez": 25,
            "intervenez": 22,
            "incendieriez": 24,
            "inoculerez": 21,
            "indurez": 17,
            "intimideriez": 23,
            "invoquiez": 28,
            "interpolerez": 23,
            "immuniserez": 22,
            "insecurisiez": 23,
            "interconnectiez": 28,
            "instituiez": 19,
            "incurviez": 23,
            "incendierez": 23,
            "incarnassiez": 23,
            "illuminez": 19,
            "incurvassiez": 26,
            "infibulerez": 25,
            "ingenierez": 20,
            "indianiserez": 22,
            "intuitassiez": 21,
            "instaurez": 18,
            "immatriculiez": 26,
            "incarcererez": 25,
            "interferiez": 23,
            "inveterassiez": 25,
            "interrogiez": 21,
            "instrumentalisez": 26,
            "insererez": 18,
            "injecteriez": 29,
            "inspecteriez": 25,
            "intubez": 18,
            "impermeabiliserez": 32,
            "intercepteriez": 27,
            "interposez": 21,
            "investiguerez": 26,
            "isoleriez": 18,
            "initialisez": 20,
            "integrerez": 20,
            "interniez": 18,
            "interfacerez": 26,
            "irriguiez": 19,
            "innoverez": 21,
            "incorporeriez": 26,
            "interposeriez": 24,
            "imprimerez": 23,
            "indurerez": 19,
            "incrementiez": 24,
            "irradierez": 20,
            "incardinez": 22,
            "internalisiez": 22,
            "ignoriez": 18,
            "indemniseriez": 24,
            "initiassiez": 20,
            "infarciriez": 25,
            "implantiez": 22,
            "ignifugeassiez": 28,
            "imprimassiez": 25,
            "inventoriiez": 24,
            "illustrassiez": 22,
            "integrez": 18,
            "interioriseriez": 24,
            "intriquiez": 26,
            "intrigueriez": 22,
            "interpelerez": 23,
            "introspecterez": 27,
            "instrumentalisassiez": 30,
            "indiquassiez": 29,
            "impactiez": 23,
            "interfoliiez": 24,
            "impregniez": 23,
            "insuffleriez": 27,
            "interconnectassiez": 31,
            "injecterez": 28,
            "introjecteriez": 32,
            "informez": 21,
            "infesterez": 22,
            "inventorierez": 25,
            "insolubilisiez": 25,
            "irritez": 16,
            "introduisez": 21,
            "invitez": 19,
            "incinerez": 20,
            "invectivez": 27,
            "imbibez": 21,
            "interrogerez": 22,
            "internalisez": 21,
            "interveniez": 23,
            "infatuez": 20,
            "inferiorisiez": 25,
            "instrumentez": 22,
            "interconnectez": 27,
            "introduiriez": 22,
            "inventeriez": 23,
            "impressionnez": 25,
            "intercederiez": 25,
            "investiriez": 23,
            "irisez": 15,
            "immisciez": 22,
            "insonoriserez": 22,
            "insultez": 17,
            "isomeriserez": 22,
            "inalperiez": 21,
            "incriminiez": 23,
            "interpelez": 21,
            "immuniseriez": 23,
            "ixassiez": 26,
            "inquieteriez": 28,
            "illusionnassiez": 24,
            "informatisassiez": 29,
            "immergez": 20,
            "indulgencierez": 27,
            "ingurgitiez": 22,
            "imprimiez": 22,
            "intimiez": 18,
            "importunez": 22,
            "infantilisiez": 25,
            "indulgencieriez": 28,
            "infroissabiliseriez": 33,
            "invertiriez": 23,
            "irriguez": 18,
            "impatientassiez": 27,
            "indifferiez": 27,
            "infroissabilisassiez": 34,
            "inveterez": 21,
            "instrumentaliseriez": 29,
            "indaguassiez": 23,
            "imploreriez": 23,
            "incommoderez": 26,
            "infeoderiez": 24,
            "inoculassiez": 23,
            "interpelliez": 23,
            "interpretez": 22,
            "invectiverez": 29,
            "infestassiez": 24,
            "inhaliez": 20,
            "inonderez": 19,
            "incurverez": 24,
            "interjetiez": 27,
            "indiquerez": 27,
            "illusionnerez": 22,
            "instrumentalisiez": 27,
            "incrimineriez": 25,
            "incubassiez": 24,
            "insolassiez": 20,
            "incrementassiez": 27,
            "interpellassiez": 26,
            "immergeriez": 23,
            "interconnecterez": 29,
            "indifferez": 26,
            "insensibiliseriez": 28,
            "intoxiquiez": 36,
            "innocentiez": 22,
            "inflechissez": 29,
            "inondassiez": 21,
            "insensibilisez": 25,
            "imaginerez": 21,
            "interlignassiez": 25,
            "imputerez": 21,
            "indiqueriez": 28,
            "imposez": 19,
            "interagissiez": 23,
            "ignifugez": 23,
            "isomerisez": 20,
            "incarcerez": 23,
            "inculpiez": 22,
            "illumineriez": 22,
            "imputeriez": 22,
            "interfacez": 24,
            "imbriquassiez": 32,
            "islamisassiez": 23,
            "interviewassiez": 36,
            "intaillez": 18,
            "improviseriez": 28,
            "invaginez": 22,
            "ixeriez": 25,
            "imbriqueriez": 31,
            "idolatrez": 19,
            "injurieriez": 27,
            "inseminassiez": 23,
            "intimidiez": 21,
            "ionisiez": 17,
            "inseriez": 17,
            "innocenterez": 23,
            "insinuiez": 18,
            "intellectualisassiez": 31,
            "infuseriez": 22,
            "ironisez": 17,
            "installiez": 19,
            "initialerez": 20,
            "intellectualiseriez": 30,
            "influez": 19,
            "investissez": 23,
            "improuviez": 25,
            "invaginiez": 23,
            "imploserez": 22,
            "infligez": 21,
            "instillez": 18,
            "illuteriez": 19,
            "intentez": 17,
            "incendiez": 21,
            "infirmiez": 22,
            "invalidiez": 23,
            "intimidassiez": 24,
            "investissiez": 24,
            "immigrerez": 22,
            "indiceriez": 22,
            "ignorez": 17,
            "instaureriez": 21,
            "interloquiez": 28,
            "intriqueriez": 28,
            "instauriez": 19,
            "imaginiez": 20,
            "illutassiez": 20,
            "intimiderez": 22,
            "ioulerez": 17,
            "isomeriseriez": 23,
            "ingeniiez": 19,
            "innerviez": 21,
            "insupporterez": 26,
            "intentiez": 18,
            "ingererez": 19,
            "insculpassiez": 26,
            "interferez": 22,
            "influerez": 21,
            "intoxiquerez": 37,
            "insufflassiez": 28,
            "inventez": 20,
            "interrompissiez": 27,
            "inquietassiez": 29,
            "informatiserez": 27,
            "infibuleriez": 26,
            "inversassiez": 24,
            "infereriez": 22,
            "insinuassiez": 21,
            "internaliserez": 23,
            "iodliez": 17,
            "isomerisassiez": 24,
            "insinuez": 17,
            "inquieterez": 27,
            "inhumeriez": 23,
            "insereriez": 19,
            "indignassiez": 23,
            "ioderiez": 18,
            "integrassiez": 22,
            "importassiez": 24,
            "influenciez": 25,
            "intensifiiez": 24,
            "incluriez": 20,
            "indianisiez": 21,
            "induisissiez": 22,
            "insulterez": 19,
            "irradieriez": 21,
            "intoxiqueriez": 38,
            "injurierez": 26,
            "interdissiez": 22,
            "indiffererez": 28,
            "intaillassiez": 22,
            "indifferassiez": 30,
            "immobilisez": 24,
            "improuveriez": 27,
            "incluez": 18,
            "inclurez": 19,
            "intensifiez": 23,
            "ignifugerez": 25,
            "infirmassiez": 25,
            "immiscerez": 23,
            "interiorisassiez": 25,
            "incitiez": 19,
            "irriguerez": 20,
            "induriez": 18,
            "insculperez": 24,
            "immunisez": 20,
            "incorporez": 23,
            "inerteriez": 19,
            "infibulez": 23,
            "ingurgiterez": 23,
            "insecuriseriez": 25,
            "instiguerez": 21,
            "infantilisez": 24,
            "insoliez": 17,
            "inventoriassiez": 27,
            "incrustassiez": 24,
            "intercalerez": 23,
            "invertissiez": 24,
            "inferiez": 20,
            "ingerassiez": 21,
            "instruisissiez": 23,
            "infusiez": 20,
            "interloquassiez": 31,
            "interpenetreriez": 27,
            "impetrerez": 22,
            "imprimez": 21,
            "impermeabiliseriez": 33,
            "importerez": 22,
            "instituassiez": 22,
            "inscririez": 21,
            "inverserez": 22,
            "implanterez": 23,
            "interfolieriez": 26,
            "invetereriez": 24,
            "initiiez": 17,
            "incitassiez": 22,
            "incardinassiez": 26,
            "infeodiez": 22,
            "informatisez": 25,
            "interpoliez": 22,
            "indaguez": 19,
            "incuberiez": 23,
            "interpenetrerez": 26,
            "intervertiriez": 26,
            "innoveriez": 22,
            "indexez": 26,
            "interviendrez": 26,
            "inseminiez": 20,
            "idealiserez": 21,
            "infirmerez": 23,
            "insculpez": 22,
            "interpretassiez": 26
        },
        {
            "isogonal": 9,
            "inaugural": 10,
            "intervertebral": 19,
            "institutionnel": 14,
            "ileal": 5,
            "imaginal": 10,
            "inertiel": 8,
            "infrastructurel": 20,
            "infernal": 11,
            "inessentiel": 11,
            "illuvial": 11,
            "impulsionnel": 15,
            "interlingual": 13,
            "incorporel": 14,
            "infinitesimal": 17,
            "idiolectal": 13,
            "initial": 7,
            "impersonnel": 14,
            "incivil": 12,
            "interprovincial": 22,
            "individuel": 15,
            "inferentiel": 14,
            "instinctuel": 13,
            "interindustriel": 16,
            "immoral": 9,
            "indol": 6,
            "intercotidal": 15,
            "infraliminal": 16,
            "intertribal": 13,
            "ideal": 6,
            "industriel": 11,
            "inconditionnel": 17,
            "inusuel": 7,
            "interracial": 13,
            "irreel": 6,
            "intersexuel": 20,
            "il": 2,
            "interzonal": 19,
            "inamical": 11,
            "ileocaecal": 14,
            "interdigital": 14,
            "isorel": 6,
            "ichtyol": 21,
            "impartial": 12,
            "immemorial": 13,
            "informel": 12,
            "immateriel": 12,
            "intellectuel": 14,
            "interventionnel": 18,
            "intercantonal": 15,
            "intersideral": 13,
            "international": 13,
            "imperial": 11,
            "intertropical": 17,
            "inegal": 7,
            "incremental": 14,
            "integral": 9,
            "insurrectionnel": 17,
            "interpersonnel": 16,
            "intertextuel": 21,
            "illegal": 8,
            "immortel": 10,
            "indiciel": 11,
            "interindividuel": 20,
            "interfacial": 16,
            "intensionnel": 12,
            "ipsilateral": 13,
            "interactionnel": 16,
            "interastral": 11,
            "interstitiel": 12,
            "icosaedral": 13,
            "irrationnel": 11,
            "inhabituel": 15,
            "intertidal": 11,
            "interculturel": 15,
            "inactuel": 10,
            "instrumental": 13,
            "interregional": 14,
            "interferentiel": 17,
            "inquisitorial": 20,
            "informationnel": 18,
            "infralittoral": 16,
            "incrementiel": 15,
            "intestinal": 10,
            "intercommunal": 17,
            "intentionnel": 12,
            "inguinal": 9,
            "ideel": 6,
            "intersyndical": 25,
            "interfederal": 16,
            "inconel": 9,
            "intermodal": 12,
            "intracerebral": 17,
            "intrafamilial": 17,
            "indophenol": 16,
            "interparietal": 15,
            "intemporel": 13,
            "isoclinal": 11,
            "intercostal": 13
        },
        {
            "voussoyees": 22,
            "vermoulant": 14,
            "vermoulee": 13,
            "vadrouilleras": 17,
            "verrouillions": 16,
            "voulez": 18,
            "vougeots": 12,
            "voudrai": 11,
            "vermoulas": 13,
            "ventousates": 14,
            "vouterais": 12,
            "vermoulerez": 24,
            "velouter": 11,
            "veloutasse": 13,
            "voyoucratie": 25,
            "vadrouilleront": 18,
            "voussoyat": 21,
            "voutas": 9,
            "vouloir": 10,
            "vouees": 9,
            "vadrouilleur": 16,
            "voussoyassions": 26,
            "veloutes": 11,
            "vouvoyassent": 27,
            "veloutassent": 15,
            "voyoucraties": 26,
            "vasouillages": 16,
            "vogoule": 11,
            "veloutines": 13,
            "veloutement": 15,
            "vaudoue": 11,
            "verrouillee": 14,
            "verrouillasse": 16,
            "voussoyes": 21,
            "vadrouillerez": 26,
            "vouvray": 22,
            "veloute": 10,
            "vouerais": 11,
            "vouera": 9,
            "vousoyames": 23,
            "vadrouillerai": 17,
            "voussoyas": 21,
            "veloutat": 11,
            "voutions": 11,
            "vouvoyons": 24,
            "vancouveroises": 22,
            "velouterait": 14,
            "vermoulerais": 16,
            "veloutements": 16,
            "vasouillons": 14,
            "vousoya": 19,
            "voulues": 10,
            "verrouilleront": 17,
            "vouvoieront": 17,
            "vermoulasse": 15,
            "verrouiller": 14,
            "vasouillames": 16,
            "vouvoya": 22,
            "vasouillait": 14,
            "ventousais": 13,
            "vasouiller": 13,
            "vouas": 8,
            "verrouillent": 15,
            "voussoir": 11,
            "vouaient": 11,
            "vasouillassiez": 26,
            "vouterent": 12,
            "vermoulue": 13,
            "vasouillerais": 16,
            "vautour": 10,
            "voulait": 10,
            "verrouilleuse": 16,
            "voussoyassent": 25,
            "veloutas": 11,
            "ventouseriez": 24,
            "vermouths": 16,
            "verrouillates": 16,
            "velouteraient": 16,
            "voussoyee": 21,
            "vermoulure": 14,
            "verrou": 9,
            "vouvoyer": 23,
            "vouter": 9,
            "voussoyer": 21,
            "velouteriez": 23,
            "ventousassent": 16,
            "voussoieront": 15,
            "vogoules": 12,
            "vasouillais": 14,
            "vigoureuses": 15,
            "voutasse": 11,
            "vouvoyat": 23,
            "vadrouilla": 14,
            "veloutez": 20,
            "vouvoyames": 26,
            "velouterais": 14,
            "ventousai": 12,
            "vouvoient": 15,
            "ventouseront": 15,
            "vousoyat": 20,
            "vasouilleriez": 25,
            "vouta": 8,
            "voutez": 18,
            "vermoulent": 14,
            "voussoierez": 23,
            "vaudou": 10,
            "vousoye": 19,
            "voussoya": 20,
            "ventousant": 13,
            "vousoyer": 20,
            "vouiez": 18,
            "voussoiements": 17,
            "vasouilleras": 15,
            "vermouliez": 23,
            "voutaient": 12,
            "veloutai": 11,
            "voussoyates": 23,
            "voussoieras": 14,
            "voulurent": 12,
            "vadrouillerions": 19,
            "voulumes": 12,
            "vousoieront": 14,
            "vasouillent": 14,
            "ventousait": 13,
            "ventousasses": 15,
            "vasouillat": 13,
            "vousseaux": 21,
            "veloutassions": 16,
            "vouvoyassions": 28,
            "vouvoyas": 23,
            "vadrouilleraient": 20,
            "vousoierons": 14,
            "vousoyez": 29,
            "vousoyee": 20,
            "ventousera": 13,
            "vermoula": 12,
            "vermoulerai": 15,
            "verrouillaient": 17,
            "ventousez": 21,
            "ventouserent": 15,
            "vadrouillait": 16,
            "voutiez": 19,
            "vesou": 8,
            "verrouillerait": 17,
            "voutasses": 12,
            "vouait": 9,
            "vouvoyassiez": 36,
            "vougeot": 11,
            "vermoules": 13,
            "vousoieras": 13,
            "veloutions": 13,
            "vouteriez": 21,
            "vadrouillent": 16,
            "voutains": 11,
            "ventousat": 12,
            "vouteraient": 14,
            "vishnouismes": 19,
            "vouvoyai": 23,
            "vatrouchka": 27,
            "vermoulerent": 16,
            "verrouillait": 15,
            "vasouilla": 12,
            "vouvoyates": 25,
            "voutassent": 13,
            "vermoulues": 14,
            "vasouillerai": 15,
            "vouasse": 10,
            "voyous": 18,
            "vouvoyes": 23,
            "vadrouillerent": 18,
            "vadrouillas": 15,
            "veloutant": 12,
            "vermoulez": 22,
            "voue": 7,
            "vousoiements": 16,
            "vigousses": 13,
            "voussoyant": 22,
            "verrouilles": 14,
            "ventousent": 13,
            "vasouille": 12,
            "vouvoyions": 25,
            "vaudoues": 12,
            "verrouillera": 15,
            "vouvoieraient": 19,
            "vermouts": 12,
            "vouteront": 12,
            "vadrouillames": 18,
            "vroum": 9,
            "vatout": 9,
            "vigoureusement": 19,
            "vasouillerions": 17,
            "vouasses": 11,
            "verrouillas": 14,
            "vadrouillez": 24,
            "veloroutes": 13,
            "veloutieres": 14,
            "vasouillerent": 16,
            "verrouillant": 15,
            "vousoyates": 22,
            "vousoient": 12,
            "vermoulames": 16,
            "voussoyasse": 23,
            "voussoyassiez": 34,
            "verrouilleriez": 26,
            "voutons": 10,
            "voussoierai": 14,
            "voussoyerent": 24,
            "vouvoierons": 17,
            "vasouillards": 16,
            "voulais": 10,
            "vermoulees": 14,
            "ventouseras": 14,
            "voulussions": 14,
            "vadrouillai": 15,
            "vouloirs": 11,
            "voussoierait": 15,
            "vousoyais": 21,
            "verrouillassions": 19,
            "voulusse": 11,
            "voutait": 10,
            "ventousaient": 15,
            "ventousa": 11,
            "vouassent": 12,
            "veloutames": 14,
            "voudriez": 21,
            "velouterent": 14,
            "veloutiers": 13,
            "voulussiez": 22,
            "vouvoie": 13,
            "ventousassiez": 25,
            "voudrions": 13,
            "verrouillage": 16,
            "vouvoierions": 18,
            "vouvoies": 14,
            "vasouilleront": 16,
            "vermoulasses": 16,
            "verrouillages": 17,
            "vasouilles": 13,
            "vermoulions": 15,
            "vouassiez": 21,
            "vasouillez": 22,
            "velouteuse": 13,
            "vermoulais": 14,
            "visou": 8,
            "veloutais": 12,
            "vouvoierai": 16,
            "vouvoyez": 32,
            "voudrais": 12,
            "vouerez": 19,
            "vousoyassiez": 33,
            "voueront": 11,
            "vouterons": 12,
            "voussoyasses": 24,
            "vousoierez": 22,
            "vousoies": 11,
            "voutain": 10,
            "voua": 7,
            "voulions": 11,
            "voyou": 17,
            "ventouserons": 15,
            "velopousse": 15,
            "vouvoyait": 24,
            "ventouserai": 14,
            "voutant": 10,
            "voulussent": 13,
            "velouteux": 21,
            "vermoulures": 15,
            "voussoye": 20,
            "vouerions": 12,
            "vadrouilles": 15,
            "vouvoyasses": 26,
            "vermoulerait": 16,
            "vouat": 8,
            "verrous": 10,
            "veloutiere": 13,
            "vadrouillions": 17,
            "verrouillez": 23,
            "voulutes": 11,
            "vancouveroise": 21,
            "vitoulets": 12,
            "vousoiement": 15,
            "voussoyez": 30,
            "voutames": 12,
            "veloutee": 11,
            "voudraient": 14,
            "vouons": 9,
            "vasouillions": 15,
            "vouvoyiez": 33,
            "vouterions": 13,
            "vousoierions": 15,
            "voyoutes": 20,
            "vousoierait": 14,
            "velouterez": 22,
            "vadrouillerais": 18,
            "vadrouillera": 16,
            "vouvoyais": 24,
            "vousoyerent": 23,
            "veloutons": 12,
            "vermoulai": 13,
            "velouteuses": 14,
            "vermoulassions": 18,
            "voutassions": 14,
            "vasouillant": 14,
            "vousoiera": 12,
            "voussoie": 11,
            "vasouillage": 15,
            "vousoyons": 21,
            "ventouserions": 16,
            "vasouilleraient": 18,
            "vouai": 8,
            "vouates": 10,
            "vousoyees": 21,
            "vouterait": 12,
            "vouee": 8,
            "vatouts": 10,
            "veloroute": 12,
            "vasouillassions": 18,
            "vermoule": 12,
            "voulus": 9,
            "voutera": 10,
            "vouvoiera": 15,
            "voussoyaient": 24,
            "ventouseraient": 17,
            "verrouilleras": 16,
            "vouvoyasse": 25,
            "voussoiement": 16,
            "vousoyions": 22,
            "vouassions": 13,
            "ventousasse": 14,
            "vousoieraient": 16,
            "veloutasses": 14,
            "voussoient": 13,
            "verrouillat": 14,
            "vermoulus": 13,
            "vadrouilleriez": 27,
            "voussures": 12,
            "vatrouchkas": 28,
            "vouchers": 16,
            "vouez": 17,
            "ventouses": 12,
            "vermoulons": 14,
            "vousoyasse": 22,
            "voueras": 10,
            "vouvoieriez": 26,
            "veloutates": 13,
            "verrouillasses": 17,
            "velouteront": 14,
            "voudrait": 12,
            "vouerai": 10,
            "voussoirs": 12,
            "vitoulet": 11,
            "vermoulaient": 16,
            "vertuchou": 17,
            "vadrouillaient": 18,
            "vousoyai": 20,
            "voussoyais": 22,
            "vancouverois": 20,
            "voussoyames": 24,
            "voussoies": 12,
            "ventouser": 12,
            "voudra": 10,
            "vasouillarde": 16,
            "vousoierais": 14,
            "voulons": 10,
            "vermout": 11,
            "vadrouillates": 17,
            "vouvoierais": 17,
            "vousoyassent": 24,
            "voussure": 11,
            "vasouillaient": 16,
            "vousoyes": 20,
            "verrouillerez": 25,
            "voussoieraient": 17,
            "vermoulat": 13,
            "veloutait": 12,
            "vermouth": 15,
            "velouterions": 15,
            "verrouillais": 15,
            "verrouillons": 15,
            "voudront": 12,
            "vouais": 9,
            "voutat": 9,
            "vouvoiements": 19,
            "verrouillerons": 17,
            "verrouilleur": 15,
            "ventousee": 12,
            "verrouilleraient": 19,
            "vouerons": 11,
            "vadrouillasse": 17,
            "vadrouillons": 16,
            "vanouataise": 14,
            "vouvoieras": 16,
            "verrouillerions": 18,
            "vasouillates": 15,
            "variocoupleurs": 21,
            "ventousassions": 17,
            "vadrouillassions": 20,
            "vouvoyant": 24,
            "vasouillasses": 16,
            "verrouillassent": 18,
            "voudrons": 12,
            "vouges": 10,
            "vousoyas": 20,
            "voussoieriez": 24,
            "vasouillas": 13,
            "vouvoyaient": 26,
            "voucher": 15,
            "ventousions": 14,
            "vouer": 8,
            "vouvoyee": 23,
            "vermoulerons": 16,
            "velours": 10,
            "vasouillerait": 16,
            "veloutaient": 14,
            "vouames": 11,
            "vadrouillerons": 18,
            "velouterai": 13,
            "vogoul": 10,
            "voussoierions": 16,
            "voussoyai": 21,
            "vermoulates": 15,
            "voueriez": 20,
            "vouteras": 11,
            "veloutiez": 21,
            "vigousse": 12,
            "vesous": 9,
            "vouterez": 20,
            "vermouleras": 15,
            "vouerent": 11,
            "vousoierai": 13,
            "vousseau": 11,
            "velouta": 10,
            "veloutassiez": 24,
            "vousoyant": 21,
            "vanouataises": 15,
            "vishnouisme": 18,
            "variocoupleur": 20,
            "verrouillees": 15,
            "verrouillerai": 16,
            "vadrouille": 14,
            "voulu": 8,
            "vouvoyees": 24,
            "voutements": 14,
            "vouivres": 14,
            "veloutees": 12,
            "voyoute": 19,
            "ventouse": 11,
            "vermoulera": 14,
            "vermoulassent": 17,
            "vousoyiez": 30,
            "vouvoiement": 18,
            "vadrouilliez": 25,
            "voussoierais": 15,
            "voutassiez": 22,
            "verrouille": 13,
            "vouvrays": 23,
            "voulant": 10,
            "vermouleriez": 25,
            "vogouls": 11,
            "vermoulait": 14,
            "velopousses": 16,
            "verrouilleurs": 16,
            "verrouilleuses": 17,
            "vouerait": 11,
            "vouvoyerent": 26,
            "vadrouilleuse": 17,
            "vadrouillassiez": 28,
            "ventousas": 12,
            "voueraient": 13,
            "voulue": 9,
            "voulut": 9,
            "vasouilliez": 23,
            "veloutent": 12,
            "vouivre": 13,
            "vadrouillais": 16,
            "ventousiez": 22,
            "ventousees": 13,
            "voandzou": 21,
            "voussoierons": 15,
            "voussoyons": 22,
            "ventouserais": 15,
            "voutes": 9,
            "veloutier": 12,
            "vadrouiller": 15,
            "vadrouilleurs": 17,
            "verrouillassiez": 27,
            "veloutera": 12,
            "vousoie": 10,
            "voulaient": 12,
            "vadrouillat": 15,
            "vouliez": 19,
            "vermouleraient": 18,
            "voudras": 11,
            "verrouillai": 14,
            "vouvoierait": 17,
            "vadrouilleuses": 18,
            "ventouserez": 23,
            "vermoulassiez": 26,
            "vouterai": 11,
            "vousoyasses": 23,
            "verrouilla": 13,
            "vasouillera": 14,
            "vouvoierez": 25,
            "vouions": 10,
            "vigoureux": 22,
            "ventousames": 15,
            "ventousons": 13,
            "verrouillames": 17,
            "vouent": 9,
            "voulusses": 12,
            "veloutine": 12,
            "voutement": 13,
            "vasouillassent": 17,
            "vasouillerez": 24,
            "vouge": 9,
            "vasouillasse": 15,
            "voudrez": 20,
            "voutais": 10,
            "velouteras": 13,
            "voussoyait": 22,
            "vadrouillasses": 18,
            "voutates": 11,
            "vousoieriez": 23,
            "vasouillerons": 16,
            "voutai": 9,
            "vermouleront": 16,
            "voutee": 9,
            "vadrouillassent": 19,
            "vasouillard": 15,
            "vadrouillant": 16,
            "verrouillerais": 17,
            "vigoureuse": 14,
            "vousoyait": 21,
            "vouvoye": 22,
            "vousoyaient": 23,
            "verrouilliez": 24,
            "vousoyassions": 25,
            "velouterons": 14,
            "vasouillardes": 17,
            "voussoyiez": 31,
            "vaudous": 11,
            "voussoiera": 13,
            "vadrouillerait": 18,
            "voute": 8,
            "vasouillai": 13,
            "verrouillerent": 17,
            "voutent": 10,
            "vous": 7,
            "voues": 8,
            "voutees": 10,
            "vermoulerions": 17,
            "voussoyions": 23,
            "voandzous": 22,
            "vermouler": 13,
            "vanouatais": 13,
            "vautours": 11,
            "vouant": 9,
            "vermoulu": 12,
            "ventouserait": 15
        },
        {
            "virilisassiez": 25,
            "verjuterez": 29,
            "vallonniez": 22,
            "voulez": 18,
            "voletterez": 22,
            "volleyeriez": 32,
            "vitamineriez": 25,
            "violentassiez": 25,
            "vacciniez": 25,
            "virilisez": 21,
            "vapotiez": 22,
            "vermoulerez": 24,
            "voguassiez": 23,
            "verdoieriez": 24,
            "veroliez": 20,
            "ventiliez": 21,
            "vermifugerez": 29,
            "virassiez": 21,
            "vibrionnerez": 26,
            "vivoterez": 24,
            "viciassiez": 24,
            "violiez": 19,
            "vainquissiez": 31,
            "voituriez": 21,
            "voilassiez": 22,
            "vidangez": 22,
            "viciez": 20,
            "voltiez": 19,
            "viraillassiez": 25,
            "varlopiez": 23,
            "vitalisez": 21,
            "vendissiez": 23,
            "vernissez": 21,
            "vrombiriez": 25,
            "vendriez": 21,
            "verdissiez": 23,
            "vecussiez": 23,
            "viciiez": 21,
            "vacuolisiez": 25,
            "voyagez": 29,
            "vagabonderez": 28,
            "vaporiserez": 25,
            "versifiez": 24,
            "vitrez": 18,
            "vandaliseriez": 26,
            "vedettisiez": 24,
            "vadrouillerez": 26,
            "vectoriserez": 26,
            "virailliez": 22,
            "verdunisez": 23,
            "vulcanisassiez": 28,
            "velez": 17,
            "visez": 17,
            "virguliez": 22,
            "vulgariseriez": 26,
            "veinassiez": 22,
            "vanilliez": 21,
            "vidimeriez": 24,
            "violeteriez": 23,
            "vrombirez": 24,
            "venererez": 21,
            "veniez": 18,
            "violonassiez": 24,
            "vehiculerez": 28,
            "vociferassiez": 30,
            "vantiez": 19,
            "vaticinassiez": 27,
            "virevolterez": 27,
            "vautrez": 19,
            "violentiez": 22,
            "vetilleriez": 23,
            "vehiculiez": 27,
            "vitriolassiez": 25,
            "voyageassiez": 34,
            "vampez": 21,
            "vendangeassiez": 28,
            "violenterez": 23,
            "vermillonnerez": 27,
            "vectorisiez": 25,
            "vampirisez": 25,
            "verolassiez": 23,
            "virgulassiez": 25,
            "valsez": 18,
            "victimisez": 25,
            "viriliseriez": 24,
            "victimiseriez": 28,
            "visualisassiez": 26,
            "vasouillassiez": 26,
            "vieillissez": 23,
            "viniez": 18,
            "vieilliriez": 23,
            "voleterez": 21,
            "voisineriez": 23,
            "vulnerabiliserez": 30,
            "validez": 20,
            "ventouseriez": 24,
            "violoniez": 21,
            "valorisez": 21,
            "vinaigrerez": 24,
            "virolez": 19,
            "verdissez": 22,
            "viendrez": 21,
            "verolez": 19,
            "velouteriez": 23,
            "verdunisassiez": 27,
            "vitalisiez": 22,
            "vociferiez": 27,
            "verriez": 19,
            "vassalisez": 22,
            "vapoteriez": 24,
            "veloutez": 20,
            "vigilassiez": 24,
            "virtualisiez": 24,
            "vitaminassiez": 26,
            "vitrifierez": 26,
            "volterez": 20,
            "vibrerez": 22,
            "valez": 17,
            "verifierez": 25,
            "vasouilleriez": 25,
            "vitriez": 19,
            "voutez": 18,
            "vermillonnez": 25,
            "voussoierez": 23,
            "vetez": 17,
            "viabilisiez": 25,
            "valserez": 20,
            "voguerez": 21,
            "versifieriez": 27,
            "verseriez": 21,
            "vaporiseriez": 26,
            "vireriez": 20,
            "vidangeassiez": 27,
            "vendrez": 20,
            "vissez": 18,
            "vouiez": 18,
            "violetiez": 21,
            "vissiez": 19,
            "vautriez": 20,
            "vermouliez": 23,
            "vaguassiez": 23,
            "victimisiez": 26,
            "versassiez": 22,
            "vituperassiez": 27,
            "vexerez": 28,
            "vinifieriez": 26,
            "vassaliserez": 24,
            "volatilisez": 23,
            "vigilez": 20,
            "votassiez": 21,
            "valoriseriez": 24,
            "valiez": 18,
            "vaquez": 25,
            "veillassiez": 23,
            "vignetterez": 24,
            "vilipendiez": 26,
            "vivoteriez": 25,
            "vousoyez": 29,
            "vivifiassiez": 30,
            "verduniseriez": 26,
            "villegiaturiez": 27,
            "verjutassiez": 31,
            "ventousez": 21,
            "vitrifieriez": 27,
            "vermifugiez": 28,
            "vectorisassiez": 28,
            "vampirisiez": 26,
            "voutiez": 19,
            "vapotez": 21,
            "vouvoyassiez": 36,
            "velerez": 19,
            "vitupererez": 25,
            "vocalisiez": 24,
            "vouteriez": 21,
            "violetassiez": 24,
            "vivifiez": 26,
            "vulgarisassiez": 27,
            "votez": 17,
            "visualiseriez": 25,
            "vagueriez": 22,
            "villegiaturerez": 28,
            "volcaniseriez": 27,
            "valideriez": 23,
            "valdinguerez": 26,
            "vulcanisez": 24,
            "vagirez": 20,
            "veilliez": 20,
            "vaccineriez": 27,
            "varlopez": 22,
            "versez": 18,
            "variiez": 19,
            "vinssiez": 20,
            "viviez": 21,
            "vagiriez": 21,
            "vaguez": 19,
            "vallonnerez": 23,
            "vermoulez": 22,
            "vinifierez": 25,
            "vociferez": 26,
            "vielleriez": 22,
            "vrillassiez": 23,
            "vexassiez": 30,
            "vegetalisassiez": 28,
            "veillez": 19,
            "vetiriez": 20,
            "verniriez": 21,
            "viellassiez": 23,
            "verifieriez": 26,
            "vinifiiez": 24,
            "vendangez": 23,
            "vinaigriez": 23,
            "vieillissiez": 24,
            "viroleriez": 22,
            "voteriez": 20,
            "varlopassiez": 26,
            "vicierez": 22,
            "vernissassiez": 25,
            "vaquassiez": 29,
            "vetillassiez": 24,
            "vedettisez": 23,
            "vacillez": 22,
            "videriez": 21,
            "vachassiez": 27,
            "vexez": 26,
            "vadrouillez": 24,
            "vampiriseriez": 28,
            "vomissez": 21,
            "vagabondiez": 27,
            "validerez": 22,
            "valsassiez": 22,
            "vasiez": 18,
            "virevoltiez": 26,
            "villegiaturez": 26,
            "violeterez": 22,
            "vignetassiez": 25,
            "virailleriez": 24,
            "veneriez": 20,
            "virtualisez": 23,
            "vivotassiez": 26,
            "virolerez": 21,
            "voussoyassiez": 34,
            "vallonnez": 21,
            "vengez": 19,
            "vaguiez": 20,
            "valorisiez": 22,
            "vegetaliserez": 26,
            "verrouilleriez": 26,
            "vehiculassiez": 30,
            "vivifieriez": 29,
            "vaincrez": 22,
            "victimisassiez": 29,
            "violonerez": 22,
            "viraillerez": 23,
            "vitrerez": 20,
            "vetilliez": 21,
            "velassiez": 21,
            "vacuolisassiez": 28,
            "verdiriez": 22,
            "vigileriez": 23,
            "verjuteriez": 30,
            "vitaminiez": 23,
            "verjutiez": 28,
            "vinez": 17,
            "voletez": 19,
            "violoneriez": 23,
            "vulgarisiez": 24,
            "vectoriseriez": 27,
            "vitalisassiez": 25,
            "vrillez": 19,
            "vendangiez": 24,
            "violacassiez": 26,
            "villegiatureriez": 29,
            "violetez": 20,
            "vrillerez": 21,
            "vissassiez": 22,
            "vetirez": 19,
            "visiez": 18,
            "vinerez": 19,
            "vaticineriez": 26,
            "voisinassiez": 24,
            "validassiez": 24,
            "vengeriez": 22,
            "viraillez": 21,
            "viseriez": 20,
            "visualisiez": 23,
            "variez": 18,
            "volatilisiez": 24,
            "vasectomiserez": 29,
            "vasectomisez": 27,
            "vehiculez": 26,
            "vetiez": 18,
            "vanillassiez": 24,
            "vaquiez": 26,
            "vasez": 17,
            "vessez": 18,
            "valoriserez": 23,
            "voudriez": 21,
            "vanilleriez": 23,
            "vetillez": 20,
            "vivotez": 22,
            "voyiez": 27,
            "vandalisiez": 24,
            "vitupereriez": 26,
            "vedettiseriez": 26,
            "validiez": 21,
            "vulnerabilisiez": 29,
            "violassiez": 22,
            "voulussiez": 22,
            "voletteriez": 23,
            "ventousassiez": 25,
            "vibrez": 20,
            "virerez": 19,
            "valseriez": 21,
            "vocifererez": 28,
            "voligeassiez": 25,
            "vacherez": 25,
            "verbaliserez": 26,
            "volatiliseriez": 26,
            "vitrioliez": 22,
            "vouassiez": 21,
            "visualiserez": 24,
            "vampassiez": 25,
            "vasouillez": 22,
            "voiturerez": 22,
            "volcanisez": 24,
            "vegetez": 20,
            "vignetez": 21,
            "vermillonniez": 26,
            "vassaliseriez": 25,
            "vouvoyez": 32,
            "vasectomisassiez": 31,
            "vouerez": 19,
            "vibrionniez": 25,
            "vampiriserez": 27,
            "vivotiez": 23,
            "vousoyassiez": 33,
            "verserez": 20,
            "vinaigreriez": 25,
            "varappez": 24,
            "vermifugeriez": 30,
            "vousoierez": 22,
            "vandalisez": 23,
            "vibriez": 21,
            "vampirisassiez": 29,
            "vitrifiassiez": 28,
            "vitrifiez": 24,
            "verdunisiez": 24,
            "voisinerez": 22,
            "visseriez": 21,
            "vernisserez": 23,
            "vitaminerez": 24,
            "vaqueriez": 28,
            "vianderiez": 23,
            "vilipenderez": 27,
            "ventilerez": 22,
            "virtualiserez": 25,
            "voguez": 19,
            "vaquerez": 27,
            "visionneriez": 24,
            "vaccinez": 24,
            "valorisassiez": 25,
            "virolassiez": 23,
            "verbaliseriez": 27,
            "verrouillez": 23,
            "vesseriez": 21,
            "vapoterez": 23,
            "vantez": 18,
            "vendez": 19,
            "vannez": 18,
            "voussoyez": 30,
            "vaticinerez": 25,
            "verolerez": 21,
            "vegetalisez": 24,
            "visiterez": 21,
            "vachiez": 24,
            "volleyez": 29,
            "verrez": 18,
            "vouvoyiez": 33,
            "volatilisassiez": 27,
            "vainquez": 27,
            "vielliez": 20,
            "vitaliserez": 23,
            "velouterez": 22,
            "virgulerez": 23,
            "vengiez": 20,
            "voltigez": 21,
            "voitureriez": 23,
            "verbalisassiez": 28,
            "vasectomiseriez": 30,
            "vanillez": 20,
            "varloperez": 24,
            "vegeteriez": 23,
            "volleyerez": 31,
            "vaselineriez": 24,
            "vidimassiez": 25,
            "venez": 17,
            "vandalisassiez": 27,
            "vessiez": 19,
            "virilisiez": 22,
            "veillerez": 21,
            "verdoyiez": 31,
            "vampiez": 22,
            "varappassiez": 28,
            "verifiassiez": 27,
            "vocifereriez": 29,
            "vilipenderiez": 28,
            "vendiez": 20,
            "vaccinassiez": 28,
            "visassiez": 21,
            "vallonneriez": 24,
            "voisinez": 20,
            "vilipendassiez": 29,
            "voileriez": 21,
            "viriez": 18,
            "veuillez": 20,
            "vitaminez": 22,
            "viellez": 19,
            "volleyassiez": 33,
            "vigiliez": 21,
            "vomissiez": 22,
            "vulcanisiez": 25,
            "virevolteriez": 28,
            "vidangiez": 23,
            "vautrerez": 21,
            "vannerez": 20,
            "vulgariserez": 25,
            "valsiez": 19,
            "vibrassiez": 24,
            "vacuolisez": 24,
            "vicieriez": 23,
            "vermillonnassiez": 29,
            "veineriez": 21,
            "viabilisassiez": 28,
            "voyagiez": 30,
            "ventilassiez": 24,
            "viserez": 19,
            "vulgarisez": 23,
            "vermillerez": 24,
            "vesserez": 20,
            "vexiez": 27,
            "visionnerez": 23,
            "vaticinez": 23,
            "vagissez": 21,
            "vogueriez": 22,
            "valdingueriez": 27,
            "vineriez": 20,
            "violentez": 21,
            "vagissiez": 22,
            "valussiez": 21,
            "vadrouilleriez": 27,
            "verifiez": 23,
            "vinaigrez": 22,
            "vouez": 17,
            "visualisez": 22,
            "ventileriez": 23,
            "violeriez": 21,
            "vitriolerez": 23,
            "vetillerez": 22,
            "vouvoieriez": 26,
            "venerassiez": 23,
            "volcanisiez": 25,
            "vegetalisiez": 25,
            "verjutez": 27,
            "vivez": 20,
            "viendriez": 22,
            "voilerez": 20,
            "voligeriez": 23,
            "veroleriez": 22,
            "volcanisassiez": 28,
            "verbalisiez": 25,
            "vapotassiez": 25,
            "vegetassiez": 24,
            "varieriez": 21,
            "venerez": 19,
            "videz": 18,
            "vieillirez": 22,
            "voilez": 18,
            "vendangeriez": 26,
            "vivriez": 22,
            "vibrionnez": 24,
            "virevoltassiez": 29,
            "vitaliseriez": 24,
            "vaselinerez": 23,
            "violaciez": 23,
            "vendangerez": 25,
            "vibrionneriez": 27,
            "vulcaniserez": 26,
            "verrouillerez": 25,
            "voltigeassiez": 26,
            "volatiliserez": 25,
            "vilipendez": 25,
            "vinassiez": 21,
            "vituperiez": 24,
            "vaporisassiez": 27,
            "versiez": 19,
            "vivifierez": 28,
            "vituperez": 23,
            "vidiez": 19,
            "vinifiassiez": 27,
            "violerez": 20,
            "vehiculeriez": 29,
            "veinerez": 20,
            "vanteriez": 21,
            "vrilliez": 20,
            "vomirez": 20,
            "vaudrez": 20,
            "vivifiiez": 27,
            "volleyiez": 30,
            "vacilleriez": 25,
            "voltigerez": 23,
            "veilleriez": 22,
            "virguleriez": 24,
            "vermifugez": 27,
            "vasassiez": 21,
            "veinez": 18,
            "violenteriez": 24,
            "voterez": 19,
            "voussoieriez": 24,
            "votiez": 18,
            "vamperiez": 24,
            "verduniserez": 25,
            "versifierez": 26,
            "vidimez": 21,
            "vaselinassiez": 25,
            "virtualisassiez": 27,
            "vitrioleriez": 24,
            "verifiiez": 24,
            "vachez": 23,
            "viroliez": 20,
            "visionnassiez": 25,
            "voiturassiez": 24,
            "vacillassiez": 26,
            "vulnerabiliseriez": 31,
            "voleteriez": 22,
            "vamperez": 23,
            "vectorisez": 24,
            "vocalisez": 23,
            "vidimerez": 23,
            "violonez": 20,
            "vassalisassiez": 26,
            "valdinguiez": 25,
            "veiniez": 19,
            "vibreriez": 23,
            "voltigiez": 22,
            "voueriez": 20,
            "virevoltez": 25,
            "veloutiez": 21,
            "vermillassiez": 26,
            "vouterez": 20,
            "vanterez": 20,
            "viandiez": 21,
            "veloutassiez": 24,
            "virgulez": 21,
            "vetissiez": 21,
            "vegeterez": 22,
            "voisiniez": 21,
            "visionniez": 22,
            "voiliez": 19,
            "vivrez": 21,
            "vexeriez": 29,
            "vandaliserez": 25,
            "violaceriez": 25,
            "vigneterez": 23,
            "vaseliniez": 22,
            "vrilleriez": 22,
            "vaseriez": 20,
            "visserez": 20,
            "vacilliez": 23,
            "vocalisassiez": 27,
            "voiturez": 20,
            "viandez": 20,
            "vousoyiez": 30,
            "vulnerabilisez": 28,
            "voletiez": 20,
            "vagabondassiez": 30,
            "vadrouilliez": 25,
            "vanillerez": 22,
            "varierez": 20,
            "valdinguassiez": 28,
            "vidassiez": 22,
            "voutassiez": 22,
            "vrombissez": 25,
            "vermouleriez": 25,
            "voguiez": 20,
            "vedettisassiez": 27,
            "vallonnassiez": 25,
            "voliez": 18,
            "vasectomisiez": 28,
            "vernirez": 20,
            "vrombissiez": 26,
            "verdirez": 21,
            "vidangeriez": 25,
            "vacillerez": 24,
            "vaticiniez": 24,
            "vermillez": 22,
            "volteriez": 21,
            "voyageriez": 32,
            "vadrouillassiez": 28,
            "vulcaniseriez": 27,
            "vessassiez": 22,
            "viabiliseriez": 27,
            "vermifugeassiez": 32,
            "versifiiez": 25,
            "vitriolez": 21,
            "viabilisez": 24,
            "vulnerabilisassiez": 32,
            "vautrassiez": 23,
            "visitez": 19,
            "violez": 18,
            "volcaniserez": 26,
            "victimiserez": 27,
            "verdoierez": 23,
            "viellerez": 21,
            "volez": 17,
            "vasouilliez": 23,
            "vignetteriez": 25,
            "ventousiez": 22,
            "venereriez": 22,
            "visitiez": 20,
            "vaguerez": 21,
            "visiteriez": 22,
            "vocaliserez": 25,
            "varloperiez": 25,
            "violetteriez": 24,
            "vaccinerez": 26,
            "vermillonneriez": 28,
            "volassiez": 21,
            "vannassiez": 22,
            "varapperiez": 27,
            "vagabonderiez": 29,
            "vengeassiez": 24,
            "voleriez": 20,
            "verrouillassiez": 27,
            "verdoyez": 30,
            "vibrionnassiez": 28,
            "vouliez": 19,
            "vignetiez": 22,
            "voligerez": 22,
            "verdoyassiez": 34,
            "vomiriez": 21,
            "voyez": 26,
            "veliez": 18,
            "vaporisez": 23,
            "ventouserez": 23,
            "varappiez": 25,
            "vermoulassiez": 26,
            "vegetiez": 21,
            "vacuoliserez": 26,
            "vidangerez": 24,
            "vaudriez": 21,
            "vernisseriez": 24,
            "vouvoierez": 25,
            "vengerez": 21,
            "ventilez": 20,
            "vacheriez": 26,
            "vitrassiez": 22,
            "versifiassiez": 28,
            "violetterez": 23,
            "viriliserez": 23,
            "vaporisiez": 24,
            "visionnez": 21,
            "vagabondez": 26,
            "vainquiez": 28,
            "vasouillerez": 24,
            "vigneteriez": 24,
            "vassalisiez": 23,
            "voudrez": 20,
            "virtualiseriez": 26,
            "vitrifiiez": 25,
            "virez": 17,
            "veleriez": 20,
            "vousoieriez": 23,
            "vanniez": 19,
            "violacerez": 24,
            "villegiaturassiez": 30,
            "volerez": 19,
            "voltassiez": 22,
            "vermilleriez": 25,
            "voltigeriez": 24,
            "vigilerez": 22,
            "vaserez": 19,
            "vinaigrassiez": 26,
            "vitreriez": 21,
            "vautreriez": 22,
            "vacuoliseriez": 27,
            "vaincriez": 23,
            "verrouilliez": 24,
            "visitassiez": 23,
            "vocaliseriez": 26,
            "viabiliserez": 26,
            "vedettiserez": 25,
            "vaselinez": 21,
            "voussoyiez": 31,
            "vantassiez": 22,
            "vinifiez": 23,
            "variassiez": 22,
            "verbalisez": 24,
            "vidimiez": 22,
            "voligez": 20,
            "voyagerez": 31,
            "vernissiez": 22,
            "viandassiez": 24,
            "vanneriez": 21,
            "voletassiez": 23,
            "voltez": 18,
            "valdinguez": 24,
            "violacez": 22,
            "vianderez": 22,
            "vermilliez": 23,
            "viderez": 20,
            "varapperez": 26,
            "voligiez": 21,
            "vegetaliseriez": 27
        },
        {
            "vicarial": 13,
            "vermeil": 11,
            "virginal": 12,
            "vitriol": 10,
            "vaccinal": 15,
            "val": 6,
            "ventral": 10,
            "vieil": 8,
            "vicomtal": 14,
            "volatil": 10,
            "varietal": 11,
            "vegetal": 11,
            "vertical": 13,
            "vavassal": 14,
            "vesperal": 13,
            "virilocal": 14,
            "visceral": 13,
            "veronal": 10,
            "venal": 8,
            "vil": 6,
            "vogoul": 10,
            "vantail": 10,
            "vital": 8,
            "vertisol": 11,
            "vicinal": 12,
            "vocationnel": 16,
            "viral": 8,
            "verbal": 11,
            "viol": 7,
            "virtuel": 10,
            "vernal": 9,
            "veniel": 9,
            "vaginal": 11,
            "vectoriel": 14,
            "vestigial": 13,
            "volleyball": 24,
            "vesical": 12,
            "vitrail": 10,
            "viril": 8,
            "vigil": 9,
            "vassal": 9,
            "vol": 6,
            "visuel": 9,
            "vagal": 9,
            "vicennal": 13,
            "vicesimal": 15,
            "vocal": 10,
            "vertebral": 14,
            "vinyl": 17,
            "ventail": 10
        }
    ]
}